github_webhook/__init__.py
github_webhook/webhook.py
github_webhook-1.0.4.dist-info/LICENSE
github_webhook-1.0.4.dist-info/METADATA
github_webhook-1.0.4.dist-info/WHEEL
github_webhook-1.0.4.dist-info/top_level.txt
github_webhook-1.0.4.dist-info/RECORD
